pixstem/__init__.py
pixstem/api.py
pixstem/cluster_tools.py
pixstem/conftest.py
pixstem/dask_test_data.py
pixstem/dask_tools.py
pixstem/diffraction_tools.py
pixstem/dpc_tools.py
pixstem/dummy_data.py
pixstem/fem_tools.py
pixstem/io_tools.py
pixstem/lazy_tools.py
pixstem/make_diffraction_test_data.py
pixstem/marker_tools.py
pixstem/pixelated_stem_class.py
pixstem/pixelated_stem_tools.py
pixstem/radial.py
pixstem/ransac_ellipse_tools.py
pixstem/tests/__init__.py
pixstem/tests/test_api.py
pixstem/tests/test_cluster_tools.py
pixstem/tests/test_dask_test_data.py
pixstem/tests/test_dask_tools.py
pixstem/tests/test_diffraction_tools.py
pixstem/tests/test_dpc_signal_class.py
pixstem/tests/test_dpc_signal_tools.py
pixstem/tests/test_dpc_tools.py
pixstem/tests/test_dummy_data.py
pixstem/tests/test_fem_tools.py
pixstem/tests/test_io_tools.py
pixstem/tests/test_lazy_tools.py
pixstem/tests/test_make_diffraction_test_data.py
pixstem/tests/test_marker_tools.py
pixstem/tests/test_pixelated_stem_class.py
pixstem/tests/test_pixelated_stem_tools.py
pixstem/tests/test_radial.py
pixstem/tests/test_ransac_ellipse_tools.py
pixstem/tests/test_tools.py
pixstem/tests/test_data/dpcbasesignal_test.hdf5
pixstem/tests/test_data/dpcbasesignal_test_too_many_signal_dims.hdf5
pixstem/tests/test_data/dpcsignal1d_test.hdf5
pixstem/tests/test_data/dpcsignal2d_test.hdf5
pixstem/tests/test_data/dpcsignal2d_test_too_many_nav_dim.hdf5
pixstem/tests/test_data/fpd_file_test.hdf5
pixstem/tests/test_data/pixelated_stem_test.hdf5
pixstem-0.4.0.dist-info/LICENSE
pixstem-0.4.0.dist-info/METADATA
pixstem-0.4.0.dist-info/WHEEL
pixstem-0.4.0.dist-info/top_level.txt
pixstem-0.4.0.dist-info/RECORD
