Metadata-Version: 2.1
Name: pixstem
Version: 0.4.0
Summary: Library for processing scanning transmission electron microscopy data acquired using a pixelated detector
Home-page: http://pixstem.org/
Author: Magnus Nord
Author-email: magnunor@gmail.com
License: GPL v3
Download-URL: https://gitlab.com/pixstem/pixstem/repository/archive.tar?ref=0.4.0
Keywords: STEM,data analysis,microscopy
Platform: UNKNOWN
Requires-Dist: scipy
Requires-Dist: numpy (>=1.13)
Requires-Dist: h5py
Requires-Dist: ipython (>=2.0)
Requires-Dist: matplotlib (>=3.1.0)
Requires-Dist: hyperspy (>=1.4)
Requires-Dist: dask
Requires-Dist: tqdm
Requires-Dist: scikit-image (>=0.15)
Requires-Dist: scikit-learn
